tkflexbox/__init__.py
tkflexbox/layout.py
tkflexbox-0.1.0.dist-info/licenses/LICENSE
tkflexbox-0.1.0.dist-info/METADATA
tkflexbox-0.1.0.dist-info/WHEEL
tkflexbox-0.1.0.dist-info/top_level.txt
tkflexbox-0.1.0.dist-info/RECORD
