Metadata-Version: 2.4
Name: tkflexbox
Version: 0.1.0
Summary: Implements flexbox like functionality to tkinter. Makes creating a reactive GUI far easier.
Author-email: Daniel Hitchcock <dan@madeupemail.com>
License: MIT
Project-URL: Homepage, https://github.com/w50111831/tkflexbox
Classifier: Programming Language :: Python :: 3
Classifier: License :: OSI Approved :: MIT License
Classifier: Operating System :: OS Independent
Requires-Python: >=3.8
License-File: LICENSE
Dynamic: license-file
